az_auto/__init__.py
az_auto/azure_backup.py
az_auto/custom_formatter.py
az_auto/git_handler.py
az_auto/logger_config.py
az_auto/main.py
az_auto/utils/__init__.py
az_auto/utils/custom_formatter.py
az_auto/utils/logger_config.py
az_automation-1.0.0.dist-info/METADATA
az_automation-1.0.0.dist-info/WHEEL
az_automation-1.0.0.dist-info/entry_points.txt
az_automation-1.0.0.dist-info/top_level.txt
az_automation-1.0.0.dist-info/RECORD
