Metadata-Version: 2.1
Name: az-automation
Version: 1.0.0
Summary: Your package description
Home-page: https://github.com/yourusername/az_auto
Author: Your Name
Author-email: your.email@example.com
License: "MIT"
Classifier: License :: OSI Approved :: MIT License
Classifier: Programming Language :: Python :: 3
Classifier: Programming Language :: Python :: 3.7
Classifier: Programming Language :: Python :: 3.8
Classifier: Programming Language :: Python :: 3.9
Requires-Python: >=3.6
Requires-Dist: colorama
